{
  "6": [
    {
      "ticker": "RTTR",
      "price": 2.0418
    }
  ],
  "25": [
    {
      "ticker": "NCTY",
      "price": 1.3101
    }
  ],
  "95": [
    {
      "ticker": "NEPT",
      "price": 4.3
    }
  ],
  "150": [
    {
      "ticker": "NBY",
      "price": 1.5
    }
  ],
  "210": [
    {
      "ticker": "NBY",
      "price": 1.5
    }
  ],
  "276": [
    {
      "ticker": "NEPT",
      "price": 4.38
    }
  ],
  "315": [
    {
      "ticker": "MHLD",
      "price": 3.15
    }
  ],
  "384": [
    {
      "ticker": "NEPT",
      "price": 4.33
    }
  ]
}