{
  "6": [
    {
      "ticker": "JNCE",
      "price": 8.3425
    }
  ],
  "25": [
    {
      "ticker": "VSTM",
      "price": 8.6343
    }
  ],
  "95": [
    {
      "ticker": "TEDU",
      "price": 7.97
    }
  ],
  "150": [
    {
      "ticker": "SYBX",
      "price": 9.6998
    }
  ],
  "210": [
    {
      "ticker": "PBR",
      "price": 9.47
    }
  ],
  "276": [
    {
      "ticker": "EURN",
      "price": 9.4
    }
  ],
  "315": [
    {
      "ticker": "EURN",
      "price": 9.4
    }
  ],
  "384": [
    {
      "ticker": "EURN",
      "price": 9.5
    }
  ]
}