{
  "4": [
    {
      "ticker": "AFH",
      "price": 11.1
    },
    {
      "ticker": "FPRX",
      "price": 14.08
    }
  ],
  "40": [
    {
      "ticker": "RFIL",
      "price": 12
    },
    {
      "ticker": "IMMR",
      "price": 11.55
    }
  ],
  "100": [
    {
      "ticker": "VKTX",
      "price": 11.35
    },
    {
      "ticker": "EDUC",
      "price": 13.175
    }
  ],
  "200": [
    {
      "ticker": "EDUC",
      "price": 13.15
    },
    {
      "ticker": "VKTX",
      "price": 11.23
    }
  ],
  "260": [
    {
      "ticker": "EDUC",
      "price": 13.3
    },
    {
      "ticker": "VKTX",
      "price": 11.27
    }
  ],
  "351": [
    {
      "ticker": "EDUC",
      "price": 13.4
    },
    {
      "ticker": "VKTX",
      "price": 11.33
    }
  ],
  "381": [
    {
      "ticker": "EDUC",
      "price": 13.25
    },
    {
      "ticker": "VKTX",
      "price": 11.36
    }
  ]
}