{
  "4": [
    {
      "ticker": "VKTX",
      "price": 9.905
    },
    {
      "ticker": "ECYT",
      "price": 12.84
    }
  ],
  "40": [
    {
      "ticker": "CRK",
      "price": 10.97
    },
    {
      "ticker": "ASLN",
      "price": 9.97
    }
  ],
  "100": [
    {
      "ticker": "NGVC",
      "price": 11.73
    },
    {
      "ticker": "CRK",
      "price": 10.94
    }
  ],
  "200": [
    {
      "ticker": "ASLN",
      "price": 10.24
    },
    {
      "ticker": "NSTG",
      "price": 14.56
    }
  ],
  "260": [
    {
      "ticker": "ASLN",
      "price": 9.95
    },
    {
      "ticker": "OAS",
      "price": 12.95
    }
  ],
  "351": [
    {
      "ticker": "ECYT",
      "price": 12.92
    },
    {
      "ticker": "OAS",
      "price": 13.05
    }
  ],
  "381": [
    {
      "ticker": "ECYT",
      "price": 12.92
    },
    {
      "ticker": "ASLN",
      "price": 10.01
    }
  ]
}