{
  "350": [
    {
      "ticker": "UVXY",
      "price": 13.7648
    },
    {
      "ticker": "SVRA",
      "price": 10.3
    },
    {
      "ticker": "EVIX",
      "price": 12
    },
    {
      "ticker": "CRVS",
      "price": 12.435
    },
    {
      "ticker": "FAZ",
      "price": 11.49
    }
  ],
  "380": [
    {
      "ticker": "UVXY",
      "price": 13.1699
    },
    {
      "ticker": "SVRA",
      "price": 10.5
    },
    {
      "ticker": "EVIX",
      "price": 12
    },
    {
      "ticker": "CRVS",
      "price": 12.72
    },
    {
      "ticker": "FAZ",
      "price": 11.32
    }
  ]
}