{
  "63": [
    {
      "ticker": "KGC",
      "price": 2.73
    },
    {
      "ticker": "ZNGA",
      "price": 4.02
    }
  ],
  "100": [
    {
      "ticker": "KGC",
      "price": 2.735
    },
    {
      "ticker": "CHK",
      "price": 4.5
    }
  ],
  "153": [
    {
      "ticker": "TRQ",
      "price": 2.125
    },
    {
      "ticker": "RAD",
      "price": 1.27
    }
  ],
  "189": [
    {
      "ticker": "GGB",
      "price": 4.245
    },
    {
      "ticker": "RAD",
      "price": 1.27
    }
  ],
  "221": [
    {
      "ticker": "AUY",
      "price": 2.535
    },
    {
      "ticker": "KGC",
      "price": 2.715
    }
  ],
  "280": [
    {
      "ticker": "AUY",
      "price": 2.535
    },
    {
      "ticker": "HK",
      "price": 4.55
    }
  ],
  "290": [
    {
      "ticker": "AVP",
      "price": 2.17
    },
    {
      "ticker": "GRPN",
      "price": 3.68
    }
  ],
  "328": [
    {
      "ticker": "HL",
      "price": 2.79
    },
    {
      "ticker": "AUY",
      "price": 2.525
    }
  ],
  "400": [
    {
      "ticker": "HL",
      "price": 2.7801
    },
    {
      "ticker": "HK",
      "price": 4.46
    }
  ],
  "430": [
    {
      "ticker": "LYG",
      "price": 3.07
    },
    {
      "ticker": "HK",
      "price": 4.46
    }
  ]
}