{
  "0": [
    {
      "ticker": "AVP",
      "price": 2.5
    },
    {
      "ticker": "ECT",
      "price": 1.895
    },
    {
      "ticker": "QRHC",
      "price": 2.45
    }
  ],
  "5": [
    {
      "ticker": "AVP",
      "price": 2.5
    },
    {
      "ticker": "ECT",
      "price": 1.895
    },
    {
      "ticker": "QRHC",
      "price": 2.45
    }
  ],
  "16": [
    {
      "ticker": "AVP",
      "price": 2.495
    },
    {
      "ticker": "ECT",
      "price": 1.845
    },
    {
      "ticker": "QRHC",
      "price": 2.45
    }
  ],
  "30": [
    {
      "ticker": "AVP",
      "price": 2.5023
    },
    {
      "ticker": "ECT",
      "price": 1.85
    },
    {
      "ticker": "EMX",
      "price": 1.1494
    }
  ]
}