{
  "4": [
    {
      "ticker": "MFA",
      "price": 7.695
    },
    {
      "ticker": "PSLV",
      "price": 6.1173
    }
  ],
  "40": [
    {
      "ticker": "NCZ",
      "price": 5.984
    },
    {
      "ticker": "NYMT",
      "price": 6.165
    }
  ],
  "100": [
    {
      "ticker": "ZIXI",
      "price": 5.425
    },
    {
      "ticker": "SRC",
      "price": 8.655
    }
  ],
  "200": [
    {
      "ticker": "ABR",
      "price": 9.45
    },
    {
      "ticker": "FUND",
      "price": 7.9574
    }
  ],
  "260": [
    {
      "ticker": "NCZ",
      "price": 5.9805
    },
    {
      "ticker": "GSUM",
      "price": 6.29
    }
  ],
  "351": [
    {
      "ticker": "LEO",
      "price": 7.63
    },
    {
      "ticker": "IRT",
      "price": 9.48
    }
  ],
  "381": [
    {
      "ticker": "PCF",
      "price": 9.24
    },
    {
      "ticker": "NIM",
      "price": 9.69
    }
  ]
}