{
  "40": [
    {
      "ticker": "WWR",
      "price": 0.1698
    }
  ],
  "80": [
    {
      "ticker": "GRPN",
      "price": 3.88
    }
  ],
  "100": [
    {
      "ticker": "BLDP",
      "price": 3.665
    }
  ],
  "140": [
    {
      "ticker": "BLDP",
      "price": 3.73
    }
  ],
  "198": [
    {
      "ticker": "BLDP",
      "price": 3.7
    }
  ],
  "250": [
    {
      "ticker": "BLDP",
      "price": 3.705
    }
  ],
  "300": [
    {
      "ticker": "ONTX",
      "price": 0.521
    }
  ]
}