{
  "6": [
    {
      "ticker": "SILJ",
      "price": 8.7108
    }
  ],
  "25": [
    {
      "ticker": "NYNY",
      "price": 9.75
    }
  ],
  "95": [
    {
      "ticker": "NATR",
      "price": 8.95
    }
  ],
  "150": [
    {
      "ticker": "NATR",
      "price": 8.9968
    }
  ],
  "210": [
    {
      "ticker": "NTRP",
      "price": 8.75
    }
  ],
  "276": [
    {
      "ticker": "SRCI",
      "price": 8.86
    }
  ],
  "315": [
    {
      "ticker": "KOS",
      "price": 9.12
    }
  ],
  "384": [
    {
      "ticker": "AEYE",
      "price": 9.3
    }
  ]
}