{
  "4": [
    {
      "ticker": "JE",
      "price": 3.7001
    },
    {
      "ticker": "ISSC",
      "price": 2.5859
    }
  ],
  "40": [
    {
      "ticker": "HSGX",
      "price": 2.3064
    },
    {
      "ticker": "EVOL",
      "price": 2.5
    }
  ],
  "100": [
    {
      "ticker": "HSGX",
      "price": 2.3
    },
    {
      "ticker": "JE",
      "price": 3.559
    }
  ],
  "200": [
    {
      "ticker": "JE",
      "price": 3.5588
    },
    {
      "ticker": "CTEK",
      "price": 3.75
    }
  ],
  "260": [
    {
      "ticker": "FBIO",
      "price": 2.17
    },
    {
      "ticker": "JE",
      "price": 3.5662
    }
  ],
  "351": [
    {
      "ticker": "BKEP",
      "price": 2.825
    },
    {
      "ticker": "FVE",
      "price": 1.118
    }
  ],
  "381": [
    {
      "ticker": "MPVD",
      "price": 2.1295
    },
    {
      "ticker": "SES",
      "price": 2.79
    }
  ]
}