{
  "14": [
    {
      "ticker": "SONO",
      "price": 17.1303
    }
  ],
  "29": [
    {
      "ticker": "SONO",
      "price": 17.4401
    }
  ],
  "87": [
    {
      "ticker": "PDBC",
      "price": 18.0599
    }
  ],
  "114": [
    {
      "ticker": "PDBC",
      "price": 18.0751
    }
  ],
  "159": [
    {
      "ticker": "PDBC",
      "price": 18.1007
    }
  ],
  "190": [
    {
      "ticker": "PDBC",
      "price": 18.11
    }
  ],
  "220": [
    {
      "ticker": "PDBC",
      "price": 18.1331
    }
  ],
  "246": [
    {
      "ticker": "PDBC",
      "price": 18.14
    }
  ],
  "320": [
    {
      "ticker": "GDX",
      "price": 17.565
    }
  ],
  "340": [
    {
      "ticker": "GDX",
      "price": 17.565
    }
  ],
  "357": [
    {
      "ticker": "GDX",
      "price": 17.575
    }
  ],
  "383": [
    {
      "ticker": "GDX",
      "price": 17.57
    }
  ]
}