{
  "6": [
    {
      "ticker": "JYNT",
      "price": 8.87
    }
  ],
  "25": [
    {
      "ticker": "PVG",
      "price": 8.7
    }
  ],
  "95": [
    {
      "ticker": "CNST",
      "price": 9.665
    }
  ],
  "150": [
    {
      "ticker": "CNST",
      "price": 9.59
    }
  ],
  "210": [
    {
      "ticker": "CNST",
      "price": 9.4439
    }
  ],
  "276": [
    {
      "ticker": "RFIL",
      "price": 9.975
    }
  ],
  "315": [
    {
      "ticker": "CNST",
      "price": 9.73
    }
  ],
  "384": [
    {
      "ticker": "SILJ",
      "price": 9.36
    }
  ]
}