{
  "4": [
    {
      "ticker": "GCAP",
      "price": 8.145
    },
    {
      "ticker": "GOGO",
      "price": 9.34
    },
    {
      "ticker": "S",
      "price": 6.315
    }
  ],
  "40": [
    {
      "ticker": "CHEK",
      "price": 7.4153
    },
    {
      "ticker": "PMM",
      "price": 7.0632
    },
    {
      "ticker": "TIS",
      "price": 6.93
    }
  ],
  "100": [
    {
      "ticker": "CHEK",
      "price": 7.15
    },
    {
      "ticker": "ASPU",
      "price": 7.34
    },
    {
      "ticker": "AXTI",
      "price": 5.9
    }
  ],
  "200": [
    {
      "ticker": "CHEK",
      "price": 6.9481
    },
    {
      "ticker": "CEL",
      "price": 7.2423
    },
    {
      "ticker": "GCAP",
      "price": 7.795
    }
  ],
  "260": [
    {
      "ticker": "CHEK",
      "price": 7.3713
    },
    {
      "ticker": "GUT",
      "price": 5.88
    },
    {
      "ticker": "DVCR",
      "price": 6.835
    }
  ],
  "351": [
    {
      "ticker": "TIS",
      "price": 6.6
    },
    {
      "ticker": "GDL",
      "price": 9.36
    },
    {
      "ticker": "WAIR",
      "price": 9.8
    }
  ],
  "381": [
    {
      "ticker": "TIS",
      "price": 6.66
    },
    {
      "ticker": "AWP",
      "price": 6.349
    },
    {
      "ticker": "WAIR",
      "price": 9.925
    }
  ]
}