{
  "40": [
    {
      "ticker": "DERM",
      "price": 9.26
    },
    {
      "ticker": "AINV",
      "price": 5.605
    },
    {
      "ticker": "WPG",
      "price": 6.3382
    }
  ],
  "80": [
    {
      "ticker": "GERN",
      "price": 6.5499
    },
    {
      "ticker": "WPG",
      "price": 6.35
    },
    {
      "ticker": "AINV",
      "price": 5.5632
    }
  ],
  "100": [
    {
      "ticker": "GERN",
      "price": 5.975
    },
    {
      "ticker": "MGEN",
      "price": 7.9214
    },
    {
      "ticker": "TVIX",
      "price": 8.69
    }
  ],
  "140": [
    {
      "ticker": "PEI",
      "price": 9.7
    },
    {
      "ticker": "WPG",
      "price": 6.425
    },
    {
      "ticker": "CDE",
      "price": 7.885
    }
  ],
  "200": [
    {
      "ticker": "WPG",
      "price": 6.445
    },
    {
      "ticker": "CDE",
      "price": 7.96
    },
    {
      "ticker": "INO",
      "price": 5.2133
    }
  ],
  "250": [
    {
      "ticker": "WPG",
      "price": 6.49
    },
    {
      "ticker": "INO",
      "price": 5.34
    },
    {
      "ticker": "CDE",
      "price": 7.941
    }
  ],
  "300": [
    {
      "ticker": "WPG",
      "price": 6.465
    },
    {
      "ticker": "TVIX",
      "price": 8.85
    },
    {
      "ticker": "INO",
      "price": 5.31
    }
  ]
}