{
  "6": [
    {
      "ticker": "MARK",
      "price": 4.95
    }
  ],
  "25": [
    {
      "ticker": "BCLI",
      "price": 4.965
    }
  ],
  "95": [
    {
      "ticker": "TRIB",
      "price": 4.79
    }
  ],
  "150": [
    {
      "ticker": "ADMA",
      "price": 4.98
    }
  ],
  "210": [
    {
      "ticker": "XELA",
      "price": 4.96
    }
  ],
  "276": [
    {
      "ticker": "XELA",
      "price": 4.9897
    }
  ],
  "315": [
    {
      "ticker": "XELA",
      "price": 4.98
    }
  ],
  "384": [
    {
      "ticker": "XELA",
      "price": 4.97
    }
  ]
}