{
  "4": [
    {
      "ticker": "AFIN",
      "price": 17.1
    },
    {
      "ticker": "BRY",
      "price": 16.21
    }
  ],
  "40": [
    {
      "ticker": "AFIN",
      "price": 17.15
    },
    {
      "ticker": "CCT",
      "price": 15.94
    }
  ],
  "100": [
    {
      "ticker": "AFIN",
      "price": 17.48
    },
    {
      "ticker": "CCT",
      "price": 15.946
    }
  ],
  "200": [
    {
      "ticker": "AFIN",
      "price": 17.65
    },
    {
      "ticker": "CCT",
      "price": 15.9599
    }
  ],
  "260": [
    {
      "ticker": "AFIN",
      "price": 17.63
    },
    {
      "ticker": "CCT",
      "price": 15.9231
    }
  ],
  "351": [
    {
      "ticker": "AFIN",
      "price": 17.2
    },
    {
      "ticker": "CCT",
      "price": 15.88
    }
  ],
  "381": [
    {
      "ticker": "AFIN",
      "price": 17.44
    },
    {
      "ticker": "CCT",
      "price": 15.86
    }
  ]
}