{
  "100": [
    {
      "ticker": "MGTA",
      "price": 12.76
    }
  ],
  "153": [
    {
      "ticker": "CMTA",
      "price": 10.3799
    }
  ],
  "189": [
    {
      "ticker": "JP",
      "price": 11.9201
    }
  ],
  "221": [
    {
      "ticker": "MBNAA",
      "price": 14
    }
  ],
  "280": [
    {
      "ticker": "MBNAA",
      "price": 15
    }
  ],
  "290": [
    {
      "ticker": "XENE",
      "price": 14.3
    }
  ],
  "328": [
    {
      "ticker": "MBNAA",
      "price": 13
    }
  ],
  "360": [
    {
      "ticker": "MBNAA",
      "price": 13
    }
  ],
  "388": [
    {
      "ticker": "PLSE",
      "price": 13.1
    }
  ]
}