{
  "0": [
    {
      "ticker": "HZN",
      "price": 6.65
    },
    {
      "ticker": "ALRN",
      "price": 5.66
    }
  ],
  "5": [
    {
      "ticker": "NXEOU",
      "price": 8.44
    },
    {
      "ticker": "HZN",
      "price": 6.5
    },
    {
      "ticker": "ALRN",
      "price": 5.66
    }
  ],
  "16": [
    {
      "ticker": "NXEOU",
      "price": 8.44
    },
    {
      "ticker": "HZN",
      "price": 6.49
    },
    {
      "ticker": "ALRN",
      "price": 5.705
    }
  ],
  "30": [
    {
      "ticker": "NXEOU",
      "price": 8.44
    },
    {
      "ticker": "HZN",
      "price": 6.5
    },
    {
      "ticker": "ALRN",
      "price": 5.68
    }
  ]
}