{
  "6": [
    {
      "ticker": "CSBR",
      "price": 15.09
    }
  ],
  "25": [
    {
      "ticker": "PDEX",
      "price": 12.5
    }
  ],
  "95": [
    {
      "ticker": "DNKEY",
      "price": 13.845
    }
  ],
  "150": [
    {
      "ticker": "CEPU",
      "price": 12.08
    }
  ],
  "210": [
    {
      "ticker": "NERV",
      "price": 11.95
    }
  ],
  "276": [
    {
      "ticker": "NERV",
      "price": 12.1
    }
  ],
  "315": [
    {
      "ticker": "NERV",
      "price": 12.125
    }
  ],
  "384": [
    {
      "ticker": "BFR",
      "price": 12.1
    }
  ]
}