{
  "6": [
    {
      "ticker": "AVEO",
      "price": 2.31
    }
  ],
  "25": [
    {
      "ticker": "RSLS",
      "price": 0.0748
    }
  ],
  "95": [
    {
      "ticker": "JCP",
      "price": 1.715
    }
  ],
  "150": [
    {
      "ticker": "GNW",
      "price": 4.58
    }
  ],
  "210": [
    {
      "ticker": "SN",
      "price": 2.445
    }
  ],
  "276": [
    {
      "ticker": "TAHO",
      "price": 3.715
    }
  ],
  "315": [
    {
      "ticker": "TAHO",
      "price": 3.715
    }
  ],
  "384": [
    {
      "ticker": "NOG",
      "price": 2.8701
    }
  ]
}