{
  "4": [
    {
      "ticker": "LEJU",
      "price": 1.86
    },
    {
      "ticker": "SMIT",
      "price": 2.95
    },
    {
      "ticker": "PED",
      "price": 2.6
    },
    {
      "ticker": "DGLY",
      "price": 2.6001
    },
    {
      "ticker": "TA",
      "price": 4.4001
    }
  ],
  "40": [
    {
      "ticker": "ABAC",
      "price": 2.2246
    },
    {
      "ticker": "STAF",
      "price": 3.1054
    },
    {
      "ticker": "IZEA",
      "price": 1.606
    },
    {
      "ticker": "LEJU",
      "price": 1.8498
    },
    {
      "ticker": "RCON",
      "price": 1.6
    }
  ],
  "100": [
    {
      "ticker": "ABAC",
      "price": 2.25
    },
    {
      "ticker": "STAF",
      "price": 3.09
    },
    {
      "ticker": "IZEA",
      "price": 1.5666
    },
    {
      "ticker": "RCON",
      "price": 1.56
    },
    {
      "ticker": "RELV",
      "price": 4.6393
    }
  ],
  "200": [
    {
      "ticker": "STAF",
      "price": 3.0601
    },
    {
      "ticker": "ABAC",
      "price": 2.3
    },
    {
      "ticker": "JOB",
      "price": 2.77
    },
    {
      "ticker": "IZEA",
      "price": 1.588
    },
    {
      "ticker": "AEHR",
      "price": 2.54
    }
  ],
  "260": [
    {
      "ticker": "ABAC",
      "price": 2.225
    },
    {
      "ticker": "STAF",
      "price": 3.06
    },
    {
      "ticker": "OASM",
      "price": 1.4356
    },
    {
      "ticker": "CPAH",
      "price": 3.07
    },
    {
      "ticker": "JOB",
      "price": 2.77
    }
  ],
  "351": [
    {
      "ticker": "STAF",
      "price": 2.915
    },
    {
      "ticker": "OASM",
      "price": 1.4082
    },
    {
      "ticker": "ABAC",
      "price": 2.24
    },
    {
      "ticker": "RCON",
      "price": 1.56
    },
    {
      "ticker": "IZEA",
      "price": 1.5788
    }
  ],
  "381": [
    {
      "ticker": "STAF",
      "price": 2.92
    },
    {
      "ticker": "OASM",
      "price": 1.407
    },
    {
      "ticker": "ABAC",
      "price": 2.21
    },
    {
      "ticker": "CPAH",
      "price": 3.0201
    },
    {
      "ticker": "SAEX",
      "price": 2.0479
    }
  ]
}