{
  "6": [
    {
      "ticker": "CYTX",
      "price": 0.93
    }
  ],
  "25": [
    {
      "ticker": "AQXP",
      "price": 3.35
    }
  ],
  "95": [
    {
      "ticker": "AQXP",
      "price": 3.31
    }
  ],
  "150": [
    {
      "ticker": "CYTX",
      "price": 0.9587
    }
  ],
  "210": [
    {
      "ticker": "LINK",
      "price": 4.0573
    }
  ],
  "276": [
    {
      "ticker": "LINK",
      "price": 4.0573
    }
  ],
  "315": [
    {
      "ticker": "LINK",
      "price": 4.0573
    }
  ],
  "384": [
    {
      "ticker": "TROV",
      "price": 0.79
    }
  ]
}