{
  "200": [
    {
      "ticker": "CRK",
      "price": 10.29
    },
    {
      "ticker": "SBPH",
      "price": 13.75
    }
  ],
  "260": [
    {
      "ticker": "GSM",
      "price": 10.79
    },
    {
      "ticker": "ADTN",
      "price": 14.8
    }
  ],
  "351": [
    {
      "ticker": "CMTA",
      "price": 14.8
    },
    {
      "ticker": "HMTA",
      "price": 12.3757
    }
  ],
  "381": [
    {
      "ticker": "CMTA",
      "price": 14.9593
    },
    {
      "ticker": "NTRA",
      "price": 11.43
    }
  ]
}