{
  "6": [
    {
      "ticker": "EPM",
      "price": 9.7748
    }
  ],
  "25": [
    {
      "ticker": "AMBR",
      "price": 9.6
    }
  ],
  "95": [
    {
      "ticker": "BCOM",
      "price": 9.99
    }
  ],
  "150": [
    {
      "ticker": "BCOM",
      "price": 9.99
    }
  ],
  "210": [
    {
      "ticker": "PZN",
      "price": 9.98
    }
  ],
  "276": [
    {
      "ticker": "MXE",
      "price": 9.7
    }
  ],
  "315": [
    {
      "ticker": "MXE",
      "price": 9.7
    }
  ],
  "384": [
    {
      "ticker": "MXE",
      "price": 9.7
    }
  ]
}