{
  "4": [
    {
      "ticker": "TTPH",
      "price": 3.388
    },
    {
      "ticker": "GNW",
      "price": 4.615
    }
  ],
  "40": [
    {
      "ticker": "TROV",
      "price": 0.8378
    },
    {
      "ticker": "LLNW",
      "price": 4.96
    }
  ],
  "200": [
    {
      "ticker": "APRI",
      "price": 0.33
    },
    {
      "ticker": "IHT",
      "price": 1.73
    }
  ],
  "260": [
    {
      "ticker": "OPHT",
      "price": 2.5501
    },
    {
      "ticker": "GNW",
      "price": 4.6448
    }
  ],
  "351": [
    {
      "ticker": "DHF",
      "price": 3.1847
    },
    {
      "ticker": "TIK",
      "price": 3.05
    }
  ],
  "381": [
    {
      "ticker": "WSTL",
      "price": 2.87
    },
    {
      "ticker": "ATLC",
      "price": 2.97
    }
  ]
}