{
  "6": [
    {
      "ticker": "GGAL",
      "price": 20.17
    }
  ],
  "25": [
    {
      "ticker": "AFIN",
      "price": 15.9
    }
  ],
  "95": [
    {
      "ticker": "UUGRY",
      "price": 19.4
    }
  ],
  "150": [
    {
      "ticker": "CUO",
      "price": 16.9753
    }
  ],
  "210": [
    {
      "ticker": "CUO",
      "price": 16.9753
    }
  ],
  "276": [
    {
      "ticker": "CUO",
      "price": 16.9125
    }
  ],
  "315": [
    {
      "ticker": "CUO",
      "price": 16.97
    }
  ],
  "384": [
    {
      "ticker": "CUO",
      "price": 17
    }
  ]
}