{
  "6": [
    {
      "ticker": "QD",
      "price": 9.4
    }
  ],
  "25": [
    {
      "ticker": "DSKE",
      "price": 9.69
    }
  ],
  "95": [
    {
      "ticker": "GREK",
      "price": 9.69
    }
  ],
  "150": [
    {
      "ticker": "GREK",
      "price": 9.7
    }
  ],
  "210": [
    {
      "ticker": "GREK",
      "price": 9.705
    }
  ],
  "276": [
    {
      "ticker": "ABCD",
      "price": 9.69
    }
  ],
  "315": [
    {
      "ticker": "GREK",
      "price": 9.705
    }
  ],
  "384": [
    {
      "ticker": "GREK",
      "price": 9.695
    }
  ]
}