{
  "77": [
    {
      "ticker": "SURF",
      "price": 13.345
    },
    {
      "ticker": "BTAI",
      "price": 11
    },
    {
      "ticker": "SSP",
      "price": 12.305
    }
  ],
  "242": [
    {
      "ticker": "LNTH",
      "price": 14.25
    },
    {
      "ticker": "ROAD",
      "price": 12.23
    },
    {
      "ticker": "MRSN",
      "price": 14.91
    }
  ],
  "309": [
    {
      "ticker": "SURF",
      "price": 13.15
    },
    {
      "ticker": "LNTH",
      "price": 14.45
    },
    {
      "ticker": "MRSN",
      "price": 14.9
    }
  ]
}