{
  "40": [
    {
      "ticker": "VOXX",
      "price": 5.495
    }
  ],
  "80": [
    {
      "ticker": "VOXX",
      "price": 5.625
    }
  ],
  "100": [
    {
      "ticker": "VOXX",
      "price": 5.725
    }
  ],
  "140": [
    {
      "ticker": "DFBG",
      "price": 5.0962
    }
  ],
  "198": [
    {
      "ticker": "VOXX",
      "price": 5.525
    }
  ],
  "250": [
    {
      "ticker": "VOXX",
      "price": 5.55
    }
  ],
  "300": [
    {
      "ticker": "VOXX",
      "price": 5.425
    }
  ]
}