{
  "6": [
    {
      "ticker": "SRRA",
      "price": 2.9097
    }
  ],
  "25": [
    {
      "ticker": "ABAC",
      "price": 2.26
    }
  ],
  "95": [
    {
      "ticker": "HIHO",
      "price": 4.6743
    }
  ],
  "150": [
    {
      "ticker": "HIHO",
      "price": 4.7
    }
  ],
  "210": [
    {
      "ticker": "TCCO",
      "price": 4.5
    }
  ],
  "276": [
    {
      "ticker": "CARV",
      "price": 4.5
    }
  ],
  "315": [
    {
      "ticker": "TCCO",
      "price": 4.5
    }
  ],
  "384": [
    {
      "ticker": "CARV",
      "price": 4.5
    }
  ]
}