{
  "6": [
    {
      "ticker": "TROX",
      "price": 18.43
    }
  ],
  "25": [
    {
      "ticker": "I",
      "price": 19.47
    }
  ],
  "95": [
    {
      "ticker": "SLP",
      "price": 17.9937
    }
  ],
  "150": [
    {
      "ticker": "VYGR",
      "price": 19.18
    }
  ],
  "210": [
    {
      "ticker": "PAR",
      "price": 19.21
    }
  ],
  "276": [
    {
      "ticker": "PAR",
      "price": 19.21
    }
  ],
  "315": [
    {
      "ticker": "PAR",
      "price": 19.14
    }
  ],
  "384": [
    {
      "ticker": "BLFS",
      "price": 19.3
    }
  ]
}