{
  "40": [
    {
      "ticker": "LXU",
      "price": 9.785
    }
  ],
  "80": [
    {
      "ticker": "AUPH",
      "price": 5.8301
    }
  ],
  "100": [
    {
      "ticker": "SPN",
      "price": 9.825
    }
  ],
  "140": [
    {
      "ticker": "SWN",
      "price": 5.315
    }
  ],
  "198": [
    {
      "ticker": "NIO",
      "price": 8.734
    }
  ],
  "250": [
    {
      "ticker": "NIO",
      "price": 8.77
    }
  ],
  "300": [
    {
      "ticker": "NEPT",
      "price": 5.06
    }
  ]
}