{
  "6": [
    {
      "ticker": "HCLP",
      "price": 12.825
    }
  ],
  "25": [
    {
      "ticker": "ZAGG",
      "price": 14.9
    }
  ],
  "95": [
    {
      "ticker": "NEW",
      "price": 14.671
    }
  ],
  "150": [
    {
      "ticker": "NEW",
      "price": 14.915
    }
  ],
  "210": [
    {
      "ticker": "CIFS",
      "price": 14.84
    }
  ],
  "276": [
    {
      "ticker": "NEW",
      "price": 14.77
    }
  ],
  "315": [
    {
      "ticker": "TZOO",
      "price": 13.3
    }
  ]
}