{
  "6": [
    {
      "ticker": "NSSC",
      "price": 14.575
    }
  ],
  "25": [
    {
      "ticker": "FTSI",
      "price": 14.95
    }
  ],
  "95": [
    {
      "ticker": "SE",
      "price": 14.83
    }
  ],
  "150": [
    {
      "ticker": "SE",
      "price": 14.87
    }
  ],
  "210": [
    {
      "ticker": "RCUS",
      "price": 14.67
    }
  ],
  "276": [
    {
      "ticker": "SE",
      "price": 14.86
    }
  ],
  "315": [
    {
      "ticker": "SE",
      "price": 14.87
    }
  ],
  "384": [
    {
      "ticker": "SXCP",
      "price": 14.975
    }
  ]
}