{
  "77": [
    {
      "ticker": "SNR",
      "price": 8.33
    },
    {
      "ticker": "LXU",
      "price": 5.99
    },
    {
      "ticker": "ERII",
      "price": 8.1
    }
  ],
  "242": [
    {
      "ticker": "CRK",
      "price": 5.5399
    },
    {
      "ticker": "VTL",
      "price": 5.95
    },
    {
      "ticker": "ALRN",
      "price": 6.7288
    }
  ],
  "309": [
    {
      "ticker": "KONE",
      "price": 6.474
    },
    {
      "ticker": "CRK",
      "price": 5.585
    },
    {
      "ticker": "VTL",
      "price": 5.85
    }
  ]
}