{
  "200": [
    {
      "ticker": "AMMA",
      "price": 0.3441
    },
    {
      "ticker": "CNAT",
      "price": 4.92
    },
    {
      "ticker": "GLG",
      "price": 0.7726
    },
    {
      "ticker": "GERN",
      "price": 4.815
    },
    {
      "ticker": "LRAD",
      "price": 3.2
    }
  ],
  "260": [
    {
      "ticker": "AMMA",
      "price": 0.3695
    },
    {
      "ticker": "GLG",
      "price": 0.7635
    },
    {
      "ticker": "CNAT",
      "price": 4.9201
    },
    {
      "ticker": "GERN",
      "price": 4.735
    },
    {
      "ticker": "LRAD",
      "price": 3.1405
    }
  ],
  "351": [
    {
      "ticker": "AMMA",
      "price": 0.3699
    },
    {
      "ticker": "NWY",
      "price": 4.9
    },
    {
      "ticker": "TRPX",
      "price": 3.8027
    },
    {
      "ticker": "CNAT",
      "price": 4.9899
    },
    {
      "ticker": "LRAD",
      "price": 3.16
    }
  ],
  "381": [
    {
      "ticker": "AMMA",
      "price": 0.3687
    },
    {
      "ticker": "SSC",
      "price": 5
    },
    {
      "ticker": "NWY",
      "price": 4.9199
    },
    {
      "ticker": "TRPX",
      "price": 3.862
    },
    {
      "ticker": "GLG",
      "price": 0.79
    }
  ]
}