{
  "45": [
    {
      "ticker": "CNAT",
      "price": 5.1235
    },
    {
      "ticker": "LTRX",
      "price": 5.92
    },
    {
      "ticker": "METC",
      "price": 8.7
    },
    {
      "ticker": "CRR",
      "price": 8.9
    },
    {
      "ticker": "NOK",
      "price": 5.665
    }
  ],
  "189": [
    {
      "ticker": "LTRX",
      "price": 6.29
    },
    {
      "ticker": "METC",
      "price": 8.52
    },
    {
      "ticker": "CRR",
      "price": 8.87
    },
    {
      "ticker": "NOK",
      "price": 5.7
    },
    {
      "ticker": "DNR",
      "price": 5.3215
    }
  ]
}