{
  "25": [
    {
      "ticker": "BSQR",
      "price": 2.3675
    }
  ],
  "95": [
    {
      "ticker": "INFU",
      "price": 3.1
    }
  ],
  "150": [
    {
      "ticker": "SMTX",
      "price": 2.84
    }
  ],
  "210": [
    {
      "ticker": "SMTX",
      "price": 2.84
    }
  ],
  "276": [
    {
      "ticker": "BSQR",
      "price": 2.4
    }
  ],
  "315": [
    {
      "ticker": "VJET",
      "price": 3.5251
    }
  ],
  "384": [
    {
      "ticker": "VJET",
      "price": 3.56
    }
  ]
}