{
  "4": [
    {
      "ticker": "TPIV",
      "price": 8.1105
    },
    {
      "ticker": "S",
      "price": 5.27
    }
  ],
  "40": [
    {
      "ticker": "CLWT",
      "price": 7.2483
    },
    {
      "ticker": "AGC",
      "price": 5.79
    }
  ],
  "100": [
    {
      "ticker": "TPIV",
      "price": 7.6
    },
    {
      "ticker": "PPR",
      "price": 5.1
    }
  ],
  "200": [
    {
      "ticker": "CLWT",
      "price": 7.2
    },
    {
      "ticker": "FAT",
      "price": 7.3116
    }
  ],
  "260": [
    {
      "ticker": "TPIV",
      "price": 7.7152
    },
    {
      "ticker": "MJCO",
      "price": 5.709
    }
  ],
  "381": [
    {
      "ticker": "TPIV",
      "price": 7.73
    },
    {
      "ticker": "INDU",
      "price": 9.84
    }
  ]
}