{
  "6": [
    {
      "ticker": "ITI",
      "price": 4.95
    }
  ],
  "25": [
    {
      "ticker": "GRPN",
      "price": 4.45
    }
  ],
  "95": [
    {
      "ticker": "SALM",
      "price": 4.975
    }
  ],
  "150": [
    {
      "ticker": "CCO",
      "price": 4.55
    }
  ],
  "210": [
    {
      "ticker": "ASPN",
      "price": 4.565
    }
  ],
  "276": [
    {
      "ticker": "CCO",
      "price": 4.6
    }
  ],
  "315": [
    {
      "ticker": "CDR",
      "price": 4.61
    }
  ],
  "384": [
    {
      "ticker": "CCO",
      "price": 4.55
    }
  ]
}