{
  "25": [
    {
      "ticker": "RWLK",
      "price": 1.01
    }
  ],
  "95": [
    {
      "ticker": "HMNY",
      "price": 0.0914
    }
  ],
  "150": [
    {
      "ticker": "HMNY",
      "price": 0.0902
    }
  ],
  "210": [
    {
      "ticker": "HMNY",
      "price": 0.0924
    }
  ],
  "276": [
    {
      "ticker": "HMNY",
      "price": 0.0922
    }
  ],
  "315": [
    {
      "ticker": "HMNY",
      "price": 0.091
    }
  ],
  "384": [
    {
      "ticker": "HMNY",
      "price": 0.099
    }
  ]
}