{
  "6": [
    {
      "ticker": "TRXC",
      "price": 5.1
    }
  ],
  "25": [
    {
      "ticker": "BBD",
      "price": 7.955
    }
  ],
  "95": [
    {
      "ticker": "VER",
      "price": 7.425
    }
  ],
  "150": [
    {
      "ticker": "VER",
      "price": 7.43
    }
  ],
  "210": [
    {
      "ticker": "VER",
      "price": 7.41
    }
  ],
  "276": [
    {
      "ticker": "VER",
      "price": 7.425
    }
  ],
  "315": [
    {
      "ticker": "VER",
      "price": 7.445
    }
  ],
  "384": [
    {
      "ticker": "VER",
      "price": 7.465
    }
  ]
}