{
  "6": [
    {
      "ticker": "EGAN",
      "price": 14.3999
    }
  ],
  "25": [
    {
      "ticker": "EGAN",
      "price": 14.6499
    }
  ],
  "95": [
    {
      "ticker": "INS",
      "price": 10.5374
    }
  ],
  "150": [
    {
      "ticker": "VRAY",
      "price": 10.01
    }
  ],
  "210": [
    {
      "ticker": "AFIN",
      "price": 14.17
    }
  ],
  "276": [
    {
      "ticker": "AFIN",
      "price": 14.19
    }
  ],
  "315": [
    {
      "ticker": "CTSO",
      "price": 12.125
    }
  ],
  "384": [
    {
      "ticker": "AFIN",
      "price": 14.22
    }
  ]
}