{
  "6": [
    {
      "ticker": "DFBG",
      "price": 3.8
    }
  ],
  "25": [
    {
      "ticker": "ACHV",
      "price": 3.6305
    }
  ],
  "95": [
    {
      "ticker": "XBIO",
      "price": 3.9247
    }
  ],
  "150": [
    {
      "ticker": "HBP",
      "price": 4.61
    }
  ],
  "210": [
    {
      "ticker": "HBP",
      "price": 4.56
    }
  ],
  "276": [
    {
      "ticker": "NWY",
      "price": 4.94
    }
  ],
  "315": [
    {
      "ticker": "NWY",
      "price": 4.93
    }
  ],
  "384": [
    {
      "ticker": "NWY",
      "price": 4.9484
    }
  ]
}