{
  "100": [
    {
      "ticker": "HAIR",
      "price": 3.2
    },
    {
      "ticker": "LBIX",
      "price": 1.51
    }
  ],
  "200": [
    {
      "ticker": "HAIR",
      "price": 3.245
    },
    {
      "ticker": "TGC",
      "price": 0.9767
    }
  ],
  "260": [
    {
      "ticker": "DAC",
      "price": 2.1
    },
    {
      "ticker": "TGC",
      "price": 0.97
    }
  ],
  "351": [
    {
      "ticker": "HAIR",
      "price": 3.215
    },
    {
      "ticker": "TGC",
      "price": 0.984
    }
  ],
  "381": [
    {
      "ticker": "HAIR",
      "price": 3.2438
    },
    {
      "ticker": "LBIX",
      "price": 1.51
    }
  ]
}