{
  "4": [
    {
      "ticker": "NVIV",
      "price": 1.69
    },
    {
      "ticker": "NLST",
      "price": 0.1681
    }
  ],
  "40": [
    {
      "ticker": "LPTH",
      "price": 2.29
    },
    {
      "ticker": "AXON",
      "price": 2.37
    }
  ],
  "100": [
    {
      "ticker": "DCAR",
      "price": 1.27
    },
    {
      "ticker": "IDRA",
      "price": 1.315
    }
  ],
  "200": [
    {
      "ticker": "RENN",
      "price": 2.4103
    },
    {
      "ticker": "PTI",
      "price": 2.77
    }
  ],
  "260": [
    {
      "ticker": "AEZS",
      "price": 1.9999
    },
    {
      "ticker": "EMX",
      "price": 1.02
    }
  ]
}