{
  "6": [
    {
      "ticker": "GEVO",
      "price": 4.3861
    }
  ],
  "25": [
    {
      "ticker": "ADMP",
      "price": 4.8
    }
  ],
  "95": [
    {
      "ticker": "ADMP",
      "price": 4.725
    }
  ],
  "150": [
    {
      "ticker": "ADMP",
      "price": 4.55
    }
  ],
  "210": [
    {
      "ticker": "GEVO",
      "price": 4.2
    }
  ],
  "276": [
    {
      "ticker": "ADMP",
      "price": 4.5
    }
  ],
  "315": [
    {
      "ticker": "ADMP",
      "price": 4.5
    }
  ]
}