{
  "0": [
    {
      "ticker": "CLF",
      "price": 10.45
    },
    {
      "ticker": "UBCP",
      "price": 13.45
    },
    {
      "ticker": "SOXS",
      "price": 10.445
    },
    {
      "ticker": "USO",
      "price": 14.3351
    },
    {
      "ticker": "AMLP",
      "price": 10.555
    }
  ],
  "5": [
    {
      "ticker": "CLF",
      "price": 10.315
    },
    {
      "ticker": "UBCP",
      "price": 13.45
    },
    {
      "ticker": "SOXS",
      "price": 10.6313
    },
    {
      "ticker": "USO",
      "price": 14.3446
    },
    {
      "ticker": "AMLP",
      "price": 10.545
    }
  ],
  "16": [
    {
      "ticker": "CLF",
      "price": 10.28
    },
    {
      "ticker": "UBCP",
      "price": 13.45
    },
    {
      "ticker": "SOXS",
      "price": 10.745
    },
    {
      "ticker": "USO",
      "price": 14.3546
    },
    {
      "ticker": "MIE",
      "price": 10.3732
    }
  ],
  "30": [
    {
      "ticker": "CLF",
      "price": 10.45
    },
    {
      "ticker": "LOV",
      "price": 12.2293
    },
    {
      "ticker": "UBCP",
      "price": 13.45
    },
    {
      "ticker": "SOXS",
      "price": 10.61
    },
    {
      "ticker": "USO",
      "price": 14.38
    }
  ]
}