{
  "6": [
    {
      "ticker": "VIVE",
      "price": 3.76
    }
  ],
  "25": [
    {
      "ticker": "IPI",
      "price": 4.385
    }
  ],
  "95": [
    {
      "ticker": "SENS",
      "price": 4.38
    }
  ],
  "150": [
    {
      "ticker": "SFUN",
      "price": 4.35
    }
  ],
  "210": [
    {
      "ticker": "SFUN",
      "price": 4.315
    }
  ],
  "276": [
    {
      "ticker": "SFUN",
      "price": 4.27
    }
  ],
  "315": [
    {
      "ticker": "SFUN",
      "price": 4.255
    }
  ],
  "384": [
    {
      "ticker": "SFUN",
      "price": 4.265
    }
  ]
}