{
  "6": [
    {
      "ticker": "SLS",
      "price": 4.91
    }
  ],
  "25": [
    {
      "ticker": "STDY",
      "price": 4.5
    }
  ],
  "95": [
    {
      "ticker": "SLS",
      "price": 4.96
    }
  ],
  "150": [
    {
      "ticker": "MCF",
      "price": 4.65
    }
  ],
  "210": [
    {
      "ticker": "SLS",
      "price": 4.9601
    }
  ],
  "276": [
    {
      "ticker": "RSLS",
      "price": 3.3276
    }
  ],
  "315": [
    {
      "ticker": "MEIP",
      "price": 4.4
    }
  ],
  "384": [
    {
      "ticker": "SLS",
      "price": 4.9758
    }
  ]
}