{
  "6": [
    {
      "ticker": "BGCP",
      "price": 11.89
    }
  ],
  "25": [
    {
      "ticker": "WBAI",
      "price": 14.32
    }
  ],
  "95": [
    {
      "ticker": "EVLO",
      "price": 12.7
    }
  ],
  "150": [
    {
      "ticker": "EVLO",
      "price": 12.2468
    }
  ],
  "210": [
    {
      "ticker": "IOR",
      "price": 13.3001
    }
  ],
  "276": [
    {
      "ticker": "IOR",
      "price": 13.3001
    }
  ],
  "315": [
    {
      "ticker": "IOR",
      "price": 13.3001
    }
  ],
  "384": [
    {
      "ticker": "EWZS",
      "price": 12.93
    }
  ]
}