{
  "10": [],
  "35": [
    {
      "ticker": "DRIP",
      "price": 6.5
    },
    {
      "ticker": "YIN",
      "price": 8.04
    }
  ],
  "90": [
    {
      "ticker": "TRIL",
      "price": 5.649
    }
  ],
  "223": [
    {
      "ticker": "CATS",
      "price": 7.045
    },
    {
      "ticker": "SALT",
      "price": 7.225
    },
    {
      "ticker": "ASC",
      "price": 7.925
    },
    {
      "ticker": "AVH",
      "price": 6.8384
    },
    {
      "ticker": "EGLE",
      "price": 5.66
    }
  ]
}