{
  "6": [
    {
      "ticker": "AG",
      "price": 6.885
    }
  ],
  "25": [
    {
      "ticker": "APEN",
      "price": 8.3299
    }
  ],
  "95": [
    {
      "ticker": "RFIL",
      "price": 8.6817
    }
  ],
  "150": [
    {
      "ticker": "TEDU",
      "price": 8.74
    }
  ],
  "210": [
    {
      "ticker": "CSSE",
      "price": 9.64
    }
  ],
  "276": [
    {
      "ticker": "CSSE",
      "price": 9.64
    }
  ],
  "315": [
    {
      "ticker": "GEMP",
      "price": 7.98
    }
  ],
  "384": [
    {
      "ticker": "MRAM",
      "price": 9.62
    }
  ]
}