{
  "6": [
    {
      "ticker": "SWIR",
      "price": 20.0284
    }
  ],
  "25": [
    {
      "ticker": "OVLY",
      "price": 19.97
    }
  ],
  "95": [
    {
      "ticker": "MELR",
      "price": 19.8
    }
  ],
  "150": [
    {
      "ticker": "MELR",
      "price": 19.8
    }
  ],
  "210": [
    {
      "ticker": "MELR",
      "price": 19.8
    }
  ],
  "-23": [
    {
      "ticker": "MELR",
      "price": 19.85
    }
  ],
  "-10": [
    {
      "ticker": "MELR",
      "price": 19.85
    }
  ]
}