{
  "4": [
    {
      "ticker": "ATGFF",
      "price": 19
    },
    {
      "ticker": "FEYE",
      "price": 16.17
    },
    {
      "ticker": "LBRT",
      "price": 19.27
    },
    {
      "ticker": "CHRS",
      "price": 17.9
    },
    {
      "ticker": "RRC",
      "price": 15.41
    }
  ],
  "40": [
    {
      "ticker": "VLVLY",
      "price": 17.17
    },
    {
      "ticker": "ATTU",
      "price": 18.35
    },
    {
      "ticker": "GLP",
      "price": 18.7987
    },
    {
      "ticker": "SCS",
      "price": 15.35
    },
    {
      "ticker": "BBRC",
      "price": 17.7542
    }
  ],
  "100": [
    {
      "ticker": "SSG",
      "price": 16.2098
    },
    {
      "ticker": "ARL",
      "price": 17.11
    },
    {
      "ticker": "SSP",
      "price": 16.05
    },
    {
      "ticker": "NSANY",
      "price": 18.75
    },
    {
      "ticker": "HPE",
      "price": 16.72
    }
  ],
  "200": [
    {
      "ticker": "AGYS",
      "price": 15.835
    },
    {
      "ticker": "JSHLY",
      "price": 17.39
    },
    {
      "ticker": "SSP",
      "price": 16.14
    },
    {
      "ticker": "APTS",
      "price": 17.83
    },
    {
      "ticker": "FEYE",
      "price": 16.285
    }
  ],
  "260": [
    {
      "ticker": "BXG",
      "price": 17.77
    },
    {
      "ticker": "VRCA",
      "price": 16.75
    },
    {
      "ticker": "FF",
      "price": 15.79
    },
    {
      "ticker": "HMTA",
      "price": 15.75
    },
    {
      "ticker": "SOI",
      "price": 17.07
    }
  ],
  "351": [
    {
      "ticker": "HMTA",
      "price": 15.75
    },
    {
      "ticker": "EJPRY",
      "price": 15.43
    },
    {
      "ticker": "JSHLY",
      "price": 17.4
    },
    {
      "ticker": "ATUS",
      "price": 19.105
    },
    {
      "ticker": "FF",
      "price": 15.81
    }
  ],
  "381": [
    {
      "ticker": "PCN",
      "price": 18.95
    },
    {
      "ticker": "EAF",
      "price": 17.765
    },
    {
      "ticker": "HMTA",
      "price": 15.75
    },
    {
      "ticker": "IVC",
      "price": 16.3
    },
    {
      "ticker": "ZTO",
      "price": 17.93
    }
  ]
}