{
  "40": [
    {
      "ticker": "SEED",
      "price": 7.98
    }
  ],
  "80": [
    {
      "ticker": "NAKD",
      "price": 5.75
    }
  ],
  "100": [
    {
      "ticker": "BIOC",
      "price": 9.35
    }
  ],
  "140": [
    {
      "ticker": "BBW",
      "price": 8.5327
    }
  ],
  "198": [
    {
      "ticker": "BBW",
      "price": 8.525
    }
  ],
  "250": [
    {
      "ticker": "PIXY",
      "price": 5.074
    }
  ],
  "300": [
    {
      "ticker": "PIXY",
      "price": 5.1333
    }
  ]
}