{
  "4": [
    {
      "ticker": "HTZ",
      "price": 14.3024
    },
    {
      "ticker": "FTSI",
      "price": 12.95
    }
  ],
  "40": [
    {
      "ticker": "ITUB",
      "price": 11.115
    },
    {
      "ticker": "EEQ",
      "price": 10.395
    }
  ],
  "100": [
    {
      "ticker": "PDFS",
      "price": 11.91
    },
    {
      "ticker": "CNHI",
      "price": 10.375
    }
  ],
  "200": [
    {
      "ticker": "NES",
      "price": 11.22
    },
    {
      "ticker": "REW",
      "price": 11.67
    }
  ],
  "260": [
    {
      "ticker": "NES",
      "price": 11.22
    },
    {
      "ticker": "ZBIO",
      "price": 14.2804
    }
  ],
  "381": [
    {
      "ticker": "LFC",
      "price": 12.64
    },
    {
      "ticker": "CHU",
      "price": 12.085
    }
  ]
}