{
  "4": [
    {
      "ticker": "SNCR",
      "price": 11.65
    },
    {
      "ticker": "SMM",
      "price": 10.0856
    },
    {
      "ticker": "HIE",
      "price": 11.81
    },
    {
      "ticker": "NGL",
      "price": 12.595
    },
    {
      "ticker": "PQG",
      "price": 14.49
    }
  ],
  "40": [
    {
      "ticker": "EARN",
      "price": 11.0898
    },
    {
      "ticker": "MRCC",
      "price": 12.6826
    },
    {
      "ticker": "NFJ",
      "price": 12.87
    },
    {
      "ticker": "VTA",
      "price": 11.7658
    },
    {
      "ticker": "WHF",
      "price": 12.97
    }
  ],
  "100": [
    {
      "ticker": "MRCC",
      "price": 12.67
    },
    {
      "ticker": "USDP",
      "price": 10.925
    },
    {
      "ticker": "FMN",
      "price": 13.38
    },
    {
      "ticker": "PSP",
      "price": 12.2424
    },
    {
      "ticker": "IAE",
      "price": 10.3
    }
  ],
  "200": [
    {
      "ticker": "EGOV",
      "price": 14.4
    },
    {
      "ticker": "FET",
      "price": 12.25
    },
    {
      "ticker": "HIE",
      "price": 11.8001
    },
    {
      "ticker": "IAE",
      "price": 10.3324
    },
    {
      "ticker": "MAG",
      "price": 11.34
    }
  ],
  "260": [
    {
      "ticker": "LIVE",
      "price": 13.4
    },
    {
      "ticker": "PAK",
      "price": 13.04
    },
    {
      "ticker": "CSU",
      "price": 11.63
    },
    {
      "ticker": "USDP",
      "price": 10.9
    },
    {
      "ticker": "FMN",
      "price": 13.35
    }
  ],
  "351": [
    {
      "ticker": "PAK",
      "price": 13.0368
    },
    {
      "ticker": "CAFD",
      "price": 12.055
    },
    {
      "ticker": "FMN",
      "price": 13.349
    },
    {
      "ticker": "LCA",
      "price": 10.04
    },
    {
      "ticker": "PFL",
      "price": 11.77
    }
  ],
  "381": [
    {
      "ticker": "PAK",
      "price": 13.0368
    },
    {
      "ticker": "MRCC",
      "price": 12.65
    },
    {
      "ticker": "AMID",
      "price": 11.5605
    },
    {
      "ticker": "FMN",
      "price": 13.36
    },
    {
      "ticker": "AMRK",
      "price": 13.8
    }
  ]
}