{
  "4": [
    {
      "ticker": "RBBN",
      "price": 5.36
    },
    {
      "ticker": "TOUR",
      "price": 6.14
    },
    {
      "ticker": "XIN",
      "price": 5.31
    },
    {
      "ticker": "AU",
      "price": 9.03
    },
    {
      "ticker": "MDCA",
      "price": 7.975
    }
  ],
  "40": [
    {
      "ticker": "AKTS",
      "price": 5.1
    },
    {
      "ticker": "CPTA",
      "price": 7.9
    },
    {
      "ticker": "SHNY",
      "price": 8.25
    },
    {
      "ticker": "VER",
      "price": 6.64
    },
    {
      "ticker": "DMF",
      "price": 7.97
    }
  ],
  "100": [
    {
      "ticker": "WTID",
      "price": 9.36
    },
    {
      "ticker": "BZQ",
      "price": 7.66
    },
    {
      "ticker": "EVFM",
      "price": 6.44
    },
    {
      "ticker": "CX",
      "price": 6.794
    },
    {
      "ticker": "WEAT",
      "price": 6.33
    }
  ],
  "200": [
    {
      "ticker": "LWAY",
      "price": 5.675
    },
    {
      "ticker": "CPTA",
      "price": 7.9
    },
    {
      "ticker": "NATR",
      "price": 9.425
    },
    {
      "ticker": "PCK",
      "price": 8.1
    },
    {
      "ticker": "TRT",
      "price": 5.5192
    }
  ],
  "260": [
    {
      "ticker": "AKTS",
      "price": 5.09
    },
    {
      "ticker": "SMDD",
      "price": 9.71
    },
    {
      "ticker": "LOCO",
      "price": 9.825
    },
    {
      "ticker": "CMFN",
      "price": 8.0213
    },
    {
      "ticker": "NBR",
      "price": 7.67
    }
  ],
  "351": [
    {
      "ticker": "ADRO",
      "price": 6.975
    },
    {
      "ticker": "HMHC",
      "price": 7.475
    },
    {
      "ticker": "SCX",
      "price": 6.15
    },
    {
      "ticker": "LOCO",
      "price": 9.775
    },
    {
      "ticker": "MDLY",
      "price": 5.675
    }
  ],
  "381": [
    {
      "ticker": "ADRO",
      "price": 6.975
    },
    {
      "ticker": "SCX",
      "price": 6.15
    },
    {
      "ticker": "FSP",
      "price": 7.59
    },
    {
      "ticker": "SMDD",
      "price": 9.72
    },
    {
      "ticker": "SHNY",
      "price": 8.25
    }
  ]
}