{
  "4": [
    {
      "ticker": "HOLI",
      "price": 16.5
    },
    {
      "ticker": "CBD",
      "price": 19.97
    }
  ],
  "40": [
    {
      "ticker": "HOLI",
      "price": 17.57
    },
    {
      "ticker": "GASL",
      "price": 18.788
    }
  ],
  "100": [
    {
      "ticker": "RYB",
      "price": 19.55
    },
    {
      "ticker": "ITCI",
      "price": 19.79
    }
  ],
  "200": [
    {
      "ticker": "RYB",
      "price": 19.2535
    },
    {
      "ticker": "ITCI",
      "price": 19.76
    }
  ],
  "260": [
    {
      "ticker": "RYB",
      "price": 19.17
    },
    {
      "ticker": "ITCI",
      "price": 19.64
    }
  ],
  "351": [
    {
      "ticker": "RYB",
      "price": 19.64
    },
    {
      "ticker": "ITCI",
      "price": 19.55
    }
  ],
  "381": [
    {
      "ticker": "RYB",
      "price": 19.56
    },
    {
      "ticker": "ITCI",
      "price": 19.91
    }
  ]
}