{
  "6": [
    {
      "ticker": "TROX",
      "price": 14.4163
    }
  ],
  "25": [
    {
      "ticker": "CNX",
      "price": 14.95
    }
  ],
  "95": [
    {
      "ticker": "TROX",
      "price": 13.53
    }
  ],
  "150": [
    {
      "ticker": "TROX",
      "price": 13.83
    }
  ],
  "210": [
    {
      "ticker": "TROX",
      "price": 13.98
    }
  ],
  "276": [
    {
      "ticker": "TROX",
      "price": 13.94
    }
  ],
  "315": [
    {
      "ticker": "TROX",
      "price": 13.87
    }
  ],
  "384": [
    {
      "ticker": "ARWR",
      "price": 14.75
    }
  ]
}