{
  "25": [
    {
      "ticker": "ABUS",
      "price": 8.875
    }
  ],
  "95": [
    {
      "ticker": "AKTS",
      "price": 8.3999
    }
  ],
  "150": [
    {
      "ticker": "ABUS",
      "price": 8.911
    }
  ],
  "210": [
    {
      "ticker": "AKTS",
      "price": 8.3925
    }
  ],
  "276": [
    {
      "ticker": "AKTS",
      "price": 8.4
    }
  ],
  "315": [
    {
      "ticker": "TORC",
      "price": 8.52
    }
  ],
  "384": [
    {
      "ticker": "ABUS",
      "price": 8.75
    }
  ]
}